AUTHORS.rst
Changelog.rst
INSTALL.rst
LICENSE.rst
MANIFEST.in
README.rst
setup.py
stdeb.cfg
bin/puq
doc/PUQ.pdf
doc/source/index.rst
doc/source/overview.rst
doc/source/reference.rst
doc/source/users_guide.rst
doc/source/examples/examples.rst
doc/source/examples/rosen.rst
doc/source/reference/calibrate.rst
doc/source/reference/hdf.rst
doc/source/reference/hosts.rst
doc/source/reference/options.rst
doc/source/reference/parameters.rst
doc/source/reference/pdf.rst
doc/source/reference/psweep.rst
doc/source/reference/puqutil.rst
doc/source/reference/smolyak.rst
doc/source/reference/sweep.rst
doc/source/reference/testprogram.rst
doc/source/ug/analyze.rst
doc/source/ug/calibration.rst
doc/source/ug/callbacks.rst
doc/source/ug/correlated.rst
doc/source/ug/handling_output.rst
doc/source/ug/lhs.rst
doc/source/ug/mc.rst
doc/source/ug/options.rst
doc/source/ug/out2in.rst
doc/source/ug/pbs.rst
doc/source/ug/plotting.rst
doc/source/ug/read.rst
doc/source/ug/scaling.rst
doc/source/ug/scripting.rst
doc/source/ug/sensitivity.rst
doc/source/ug/simulations.rst
doc/source/ug/smolyak_mod.rst
doc/source/ug/smolyak_python.rst
doc/source/ug/started.rst
examples/1dpoly/lhs.py
examples/1dpoly/poly_prog.py
examples/1dpoly/smolyak.py
examples/3d/3d_lhs.py
examples/3d/3d_prog.py
examples/3d/3d_smolyak.py
examples/basic/basic.py
examples/basic/basic_prog.py
examples/calibrate/model_0.py
examples/calibrate/model_1.py
examples/calibrate/test0.py
examples/calibrate/test1.py
examples/calibrate/test2.py
examples/cavity/cav20.cas
examples/cavity/cav20.py
examples/cavity/cavityCollocation.py
examples/cavity/read_hdf5.py
examples/correlated/README
examples/correlated/c1.py
examples/correlated/c1_prog.py
examples/correlated/c2.py
examples/correlated/c2_prog.py
examples/discontinuous/1dsin/lhs.py
examples/discontinuous/1dsin/sin.py
examples/discontinuous/1dsin/smolyak.py
examples/discontinuous/ddome/lhs.py
examples/discontinuous/ddome/mc.py
examples/discontinuous/ddome/sin_prog.py
puq.egg-info/PKG-INFO
puq.egg-info/SOURCES.txt
puq.egg-info/dependency_links.txt
puq.egg-info/not-zip-safe
puq.egg-info/top_level.txt
