Metadata-Version: 1.1
Name: puq
Version: 2.2.2
Summary: PUQ Uncertainty Quantification Tool
Home-page: https://github.com/martin-hunt/puq
Author: Martin Hunt
Author-email: mmh@purdue.edu
License: Copyright (c) 2013 PUQ Authors
